{"type":"footer","name":"t:names.footer","sections":{"utilities":{"type":"footer-utilities","blocks":{"copyright":{"type":"footer-copyright","settings":{"show_powered_by":false,"font_size":"0.75rem","case":"none"},"blocks":{}},"footer_policy_list_BjQaXm":{"type":"footer-policy-list","name":"t:names.policy_list","settings":{"font_size":"0.75rem","case":"none"},"blocks":{}},"social_icons":{"type":"social-links","settings":{"facebook_url":"https:\/\/www.facebook.com","instagram_url":"https:\/\/www.instagram.com","youtube_url":"https:\/\/www.youtube.com","tiktok_url":"https:\/\/www.tiktok.com","twitter_url":"https:\/\/www.twitter.com","threads_url":"","linkedin_url":"","bluesky_url":"","snapchat_url":"","pinterest_url":"","tumblr_url":"","vimeo_url":"","custom_url":""},"blocks":{}}},"block_order":["copyright","footer_policy_list_BjQaXm","social_icons"],"settings":{"section_width":"page-width","gap":24,"divider_thickness":0,"color_scheme":"scheme-1","padding-block-start":12,"padding-block-end":16}}},"order":["utilities"]}